mylassi_xyz_lib/__init__.py
mylassi_xyz_lib/api_client.py
mylassi_xyz_lib/schemas/__init__.py
mylassi_xyz_lib/schemas/apiv2.py
mylassi_xyz_lib/schemas/documents.py
mylassi_xyz_lib/schemas/lesson_page_elements.py
mylassi_xyz_lib/schemas/lesson_pages.py
mylassi_xyz_lib/schemas/lessons.py
mylassi_xyz_lib/schemas/tags.py
mylassi_xyz_lib/schemas/users.py
mylassi_xyz_lib/services/__init__.py
mylassi_xyz_lib/services/document_service.py
mylassi_xyz-0.30.0.dist-info/METADATA
mylassi_xyz-0.30.0.dist-info/WHEEL
mylassi_xyz-0.30.0.dist-info/entry_points.txt
mylassi_xyz-0.30.0.dist-info/top_level.txt
mylassi_xyz-0.30.0.dist-info/RECORD
