Metadata-Version: 2.1
Name: mylassi-xyz
Version: 0.30.0
Summary: API for https://api.mylassi.xyz
Home-page: https://mylassi.xyz
Author: Christoph Laßmann
Author-email: csharplassi@posteo.de
License: UNKNOWN
Platform: UNKNOWN
Classifier: Programming Language :: Python :: 3
Classifier: Operating System :: OS Independent
Requires-Python: >=3.7
Requires-Dist: requests (==2.26.0)
Requires-Dist: marshmallow-dataclass (==8.5.3)
Requires-Dist: marshmallow-enum (==1.5.1)
Requires-Dist: marshmallow (==3.14.1)
